MANIFEST.in
README
setup.py
grate/__init__.py
grate/access.py
grate/atomic.py
grate/djangocompat.py
grate/githandle.py
grate/init.py
grate/main.py
grate/mongo.py
grate/server.py
grate.egg-info/PKG-INFO
grate.egg-info/SOURCES.txt
grate.egg-info/dependency_links.txt
grate.egg-info/requires.txt
grate.egg-info/top_level.txt
grate/checkers/__init__.py
grate/checkers/ldapchecker.py
grate/checkers/pubkey.py
grate/webapp/__init__.py
grate/webapp/manage.py
grate/webapp/settings.py
grate/webapp/urls.py
grate/webapp/utils.py
grate/webapp/webapp.wsgi
grate/webapp/media/css/base.css
grate/webapp/media/img/grate.png
grate/webapp/media/js/base.js
grate/webapp/sewer/__init__.py
grate/webapp/sewer/auth.py
grate/webapp/sewer/decorators.py
grate/webapp/sewer/forms.py
grate/webapp/sewer/json_views.py
grate/webapp/sewer/middleware.py
grate/webapp/sewer/models.py
grate/webapp/sewer/urls.py
grate/webapp/sewer/views.py
grate/webapp/sewer/templates/sewer/base.html
grate/webapp/sewer/templates/sewer/dberror.html
grate/webapp/sewer/templates/sewer/group_add.html
grate/webapp/sewer/templates/sewer/group_admin.html
grate/webapp/sewer/templates/sewer/group_index.html
grate/webapp/sewer/templates/sewer/group_info.html
grate/webapp/sewer/templates/sewer/group_view.html
grate/webapp/sewer/templates/sewer/index.html
grate/webapp/sewer/templates/sewer/key_index.html
grate/webapp/sewer/templates/sewer/repo_admin.html
grate/webapp/sewer/templates/sewer/repo_index.html
grate/webapp/sewer/templates/sewer/repo_info.html
grate/webapp/sewer/templates/sewer/repo_view.html
grate/webapp/sewer/templatetags/__init__.py
grate/webapp/sewer/templatetags/git_url.py
grate/webapp/templates/base.html
grate/webapp/templates/login.html
grate/webapp/templates/messages.html
scripts/grated
scripts/grated-init