Metadata-Version: 1.0
Name: grate
Version: 0.3
Summary: Single-purpose ssh server.
Home-page: .
Author: Alex Lee
Author-email: lee@ccs.neu.edu
License: UNKNOWN
Keywords: ssh django git
Platform: UNKNOWN
